Lab1/Part2.v
module part2 (SW, LEDR);
	input [9:0] SW;
	output [9:0] LEDR;
	wire s; // 1-bit select wire
	wire [3:0] X, Y, M; //  4-bit X, Y, M wires
	
	// input assignment
	assign s = SW[9];
	assign X = SW[3:0];
	assign Y = SW[7:4];
	assign M[3] = (~s & X[3]) | (s & Y[3]);
	assign M[2] = (~s & X[2]) | (s & Y[2]);
	assign M[1] = (~s & X[1]) | (s & Y[1]);
	assign M[0] = (~s & X[0]) | (s & Y[0]);
	
	// output assignment
	assign LEDR[3:0] = M;
	assign LEDR[8:4] = 0;
	assign LEDR[9] = s;
endmodule

Lab1/Part2_tb.v
`include "Part2.v"
`timescale 1ns/1ns

module part2_tb;
    reg [10:0] Sw;
    wire [9:0] Led;

    initial begin
        $dumpfile("Part2_tb.vcd");
        $dumpvars(0, part2_tb);
    end

    part2 uut (Sw[9:0], Led);

    initial begin
        for(Sw = 0; Sw < 1024; Sw = Sw + 1) #1;
        $finish;
    end
endmodule

Lab1/Part2_tb.vcd
$date
	Wed Oct 12 09:52:24 2022
$end
$version
	Icarus Verilog
$end
$timescale
	1ns
$end
$scope module part2_tb $end
$var wire 10 ! Led [9:0] $end
$var reg 11 " Sw [10:0] $end
$scope module uut $end
$var wire 10 # SW [9:0] $end
$var wire 1 $ s $end
$var wire 4 % Y [3:0] $end
$var wire 4 & X [3:0] $end
$var wire 4 ' M [3:0] $end
$var wire 10 ( LEDR [9:0] $end
$upscope $end
$upscope $end
$enddefinitions $end
#0
$dumpvars
b0 (
b0 '
b0 &
b0 %
0$
b0 #
b0 "
b0 !
$end
#1
b1 !
b1 (
b1 '
b1 &
b1 #
b1 "
#2
b10 !
b10 (
b10 '
b10 &
b10 #
b10 "
#3
b11 !
b11 (
b11 '
b11 &
b11 #
b11 "
#4
b100 !
b100 (
b100 '
b100 &
b100 #
b100 "
#5
b101 !
b101 (
b101 '
b101 &
b101 #
b101 "
#6
b110 !
b110 (
b110 '
b110 &
b110 #
b110 "
#7
b111 !
b111 (
b111 '
b111 &
b111 #
b111 "
#8
b1000 !
b1000 (
b1000 '
b1000 &
b1000 #
b1000 "
#9
b1001 !
b1001 (
b1001 '
b1001 &
b1001 #
b1001 "
#10
b1010 !
b1010 (
b1010 '
b1010 &
b1010 #
b1010 "
#11
b1011 !
b1011 (
b1011 '
b1011 &
b1011 #
b1011 "
#12
b1100 !
b1100 (
b1100 '
b1100 &
b1100 #
b1100 "
#13
b1101 !
b1101 (
b1101 '
b1101 &
b1101 #
b1101 "
#14
b1110 !
b1110 (
b1110 '
b1110 &
b1110 #
b1110 "
#15
b1111 !
b1111 (
b1111 '
b1111 &
b1111 #
b1111 "
#16
b0 !
b0 (
b0 '
b0 &
b1 %
b10000 #
b10000 "
#17
b1 !
b1 (
b1 '
b1 &
b10001 #
b10001 "
#18
b10 !
b10 (
b10 '
b10 &
b10010 #
b10010 "
#19
b11 !
b11 (
b11 '
b11 &
b10011 #
b10011 "
#20
b100 !
b100 (
b100 '
b100 &
b10100 #
b10100 "
#21
b101 !
b101 (
b101 '
b101 &
b10101 #
b10101 "
#22
b110 !
b110 (
b110 '
b110 &
b10110 #
b10110 "
#23
b111 !
b111 (
b111 '
b111 &
b10111 #
b10111 "
#24
b1000 !
b1000 (
b1000 '
b1000 &
b11000 #
b11000 "
#25
b1001 !
b1001 (
b1001 '
b1001 &
b11001 #
b11001 "
#26
b1010 !
b1010 (
b1010 '
b1010 &
b11010 #
b11010 "
#27
b1011 !
b1011 (
b1011 '
b1011 &
b11011 #
b11011 "
#28
b1100 !
b1100 (
b1100 '
b1100 &
b11100 #
b11100 "
#29
b1101 !
b1101 (
b1101 '
b1101 &
b11101 #
b11101 "
#30
b1110 !
b1110 (
b1110 '
b1110 &
b11110 #
b11110 "
#31
b1111 !
b1111 (
b1111 '
b1111 &
b11111 #
b11111 "
#32
b0 !
b0 (
b0 '
b0 &
b10 %
b100000 #
b100000 "
#33
b1 !
b1 (
b1 '
b1 &
b100001 #
b100001 "
#34
b10 !
b10 (
b10 '
b10 &
b100010 #
b100010 "
#35
b11 !
b11 (
b11 '
b11 &
b100011 #
b100011 "
#36
b100 !
b100 (
b100 '
b100 &
b100100 #
b100100 "
#37
b101 !
b101 (
b101 '
b101 &
b100101 #
b100101 "
#38
b110 !
b110 (
b110 '
b110 &
b100110 #
b100110 "
#39
b111 !
b111 (
b111 '
b111 &
b100111 #
b100111 "
#40
b1000 !
b1000 (
b1000 '
b1000 &
b101000 #
b101000 "
#41
b1001 !
b1001 (
b1001 '
b1001 &
b101001 #
b101001 "
#42
b1010 !
b1010 (
b1010 '
b1010 &
b101010 #
b101010 "
#43
b1011 !
b1011 (
b1011 '
b1011 &
b101011 #
b101011 "
#44
b1100 !
b1100 (
b1100 '
b1100 &
b101100 #
b101100 "
#45
b1101 !
b1101 (
b1101 '
b1101 &
b101101 #
b101101 "
#46
b1110 !
b1110 (
b1110 '
b1110 &
b101110 #
b101110 "
#47
b1111 !
b1111 (
b1111 '
b1111 &
b101111 #
b101111 "
#48
b0 !
b0 (
b0 '
b0 &
b11 %
b110000 #
b110000 "
#49
b1 !
b1 (
b1 '
b1 &
b110001 #
b110001 "
#50
b10 !
b10 (
b10 '
b10 &
b110010 #
b110010 "
#51
b11 !
b11 (
b11 '
b11 &
b110011 #
b110011 "
#52
b100 !
b100 (
b100 '
b100 &
b110100 #
b110100 "
#53
b101 !
b101 (
b101 '
b101 &
b110101 #
b110101 "
#54
b110 !
b110 (
b110 '
b110 &
b110110 #
b110110 "
#55
b111 !
b111 (
b111 '
b111 &
b110111 #
b110111 "
#56
b1000 !
b1000 (
b1000 '
b1000 &
b111000 #
b111000 "
#57
b1001 !
b1001 (
b1001 '
b1001 &
b111001 #
b111001 "
#58
b1010 !
b1010 (
b1010 '
b1010 &
b111010 #
b111010 "
#59
b1011 !
b1011 (
b1011 '
b1011 &
b111011 #
b111011 "
#60
b1100 !
b1100 (
b1100 '
b1100 &
b111100 #
b111100 "
#61
b1101 !
b1101 (
b1101 '
b1101 &
b111101 #
b111101 "
#62
b1110 !
b1110 (
b1110 '
b1110 &
b111110 #
b111110 "
#63
b1111 !
b1111 (
b1111 '
b1111 &
b111111 #
b111111 "
#64
b0 !
b0 (
b0 '
b0 &
b100 %
b1000000 #
b1000000 "
#65
b1 !
b1 (
b1 '
b1 &
b1000001 #
b1000001 "
#66
b10 !
b10 (
b10 '
b10 &
b1000010 #
b1000010 "
#67
b11 !
b11 (
b11 '
b11 &
b1000011 #
b1000011 "
#68
b100 !
b100 (
b100 '
b100 &
b1000100 #
b1000100 "
#69
b101 !
b101 (
b101 '
b101 &
b1000101 #
b1000101 "
#70
b110 !
b110 (
b110 '
b110 &
b1000110 #
b1000110 "
#71
b111 !
b111 (
b111 '
b111 &
b1000111 #
b1000111 "
#72
b1000 !
b1000 (
b1000 '
b1000 &
b1001000 #
b1001000 "
#73
b1001 !
b1001 (
b1001 '
b1001 &
b1001001 #
b1001001 "
#74
b1010 !
b1010 (
b1010 '
b1010 &
b1001010 #
b1001010 "
#75
b1011 !
b1011 (
b1011 '
b1011 &
b1001011 #
b1001011 "
#76
b1100 !
b1100 (
b1100 '
b1100 &
b1001100 #
b1001100 "
#77
b1101 !
b1101 (
b1101 '
b1101 &
b1001101 #
b1001101 "
#78
b1110 !
b1110 (
b1110 '
b1110 &
b1001110 #
b1001110 "
#79
b1111 !
b1111 (
b1111 '
b1111 &
b1001111 #
b1001111 "
#80
b0 !
b0 (
b0 '
b0 &
b101 %
b1010000 #
b1010000 "
#81
b1 !
b1 (
b1 '
b1 &
b1010001 #
b1010001 "
#82
b10 !
b10 (
b10 '
b10 &
b1010010 #
b1010010 "
#83
b11 !
b11 (
b11 '
b11 &
b1010011 #
b1010011 "
#84
b100 !
b100 (
b100 '
b100 &
b1010100 #
b1010100 "
#85
b101 !
b101 (
b101 '
b101 &
b1010101 #
b1010101 "
#86
b110 !
b110 (
b110 '
b110 &
b1010110 #
b1010110 "
#87
b111 !
b111 (
b111 '
b111 &
b1010111 #
b1010111 "
#88
b1000 !
b1000 (
b1000 '
b1000 &
b1011000 #
b1011000 "
#89
b1001 !
b1001 (
b1001 '
b1001 &
b1011001 #
b1011001 "
#90
b1010 !
b1010 (
b1010 '
b1010 &
b1011010 #
b1011010 "
#91
b1011 !
b1011 (
b1011 '
b1011 &
b1011011 #
b1011011 "
#92
b1100 !
b1100 (
b1100 '
b1100 &
b1011100 #
b1011100 "
#93
b1101 !
b1101 (
b1101 '
b1101 &
b1011101 #
b1011101 "
#94
b1110 !
b1110 (
b1110 '
b1110 &
b1011110 #
b1011110 "
#95
b1111 !
b1111 (
b1111 '
b1111 &
b1011111 #
b1011111 "
#96
b0 !
b0 (
b0 '
b0 &
b110 %
b1100000 #
b1100000 "
#97
b1 !
b1 (
b1 '
b1 &
b1100001 #
b1100001 "
#98
b10 !
b10 (
b10 '
b10 &
b1100010 #
b1100010 "
#99
b11 !
b11 (
b11 '
b11 &
b1100011 #
b1100011 "
#100
b100 !
b100 (
b100 '
b100 &
b1100100 #
b1100100 "
#101
b101 !
b101 (
b101 '
b101 &
b1100101 #
b1100101 "
#102
b110 !
b110 (
b110 '
b110 &
b1100110 #
b1100110 "
#103
b111 !
b111 (
b111 '
b111 &
b1100111 #
b1100111 "
#104
b1000 !
b1000 (
b1000 '
b1000 &
b1101000 #
b1101000 "
#105
b1001 !
b1001 (
b1001 '
b1001 &
b1101001 #
b1101001 "
#106
b1010 !
b1010 (
b1010 '
b1010 &
b1101010 #
b1101010 "
#107
b1011 !
b1011 (
b1011 '
b1011 &
b1101011 #
b1101011 "
#108
b1100 !
b1100 (
b1100 '
b1100 &
b1101100 #
b1101100 "
#109
b1101 !
b1101 (
b1101 '
b1101 &
b1101101 #
b1101101 "
#110
b1110 !
b1110 (
b1110 '
b1110 &
b1101110 #
b1101110 "
#111
b1111 !
b1111 (
b1111 '
b1111 &
b1101111 #
b1101111 "
#112
b0 !
b0 (
b0 '
b0 &
b111 %
b1110000 #
b1110000 "
#113
b1 !
b1 (
b1 '
b1 &
b1110001 #
b1110001 "
#114
b10 !
b10 (
b10 '
b10 &
b1110010 #
b1110010 "
#115
b11 !
b11 (
b11 '
b11 &
b1110011 #
b1110011 "
#116
b100 !
b100 (
b100 '
b100 &
b1110100 #
b1110100 "
#117
b101 !
b101 (
b101 '
b101 &
b1110101 #
b1110101 "
#118
b110 !
b110 (
b110 '
b110 &
b1110110 #
b1110110 "
#119
b111 !
b111 (
b111 '
b111 &
b1110111 #
b1110111 "
#120
b1000 !
b1000 (
b1000 '
b1000 &
b1111000 #
b1111000 "
#121
b1001 !
b1001 (
b1001 '
b1001 &
b1111001 #
b1111001 "
#122
b1010 !
b1010 (
b1010 '
b1010 &
b1111010 #
b1111010 "
#123
b1011 !
b1011 (
b1011 '
b1011 &
b1111011 #
b1111011 "
#124
b1100 !
b1100 (
b1100 '
b1100 &
b1111100 #
b1111100 "
#125
b1101 !
b1101 (
b1101 '
b1101 &
b1111101 #
b1111101 "
#126
b1110 !
b1110 (
b1110 '
b1110 &
b1111110 #
b1111110 "
#127
b1111 !
b1111 (
b1111 '
b1111 &
b1111111 #
b1111111 "
#128
b0 !
b0 (
b0 '
b0 &
b1000 %
b10000000 #
b10000000 "
#129
b1 !
b1 (
b1 '
b1 &
b10000001 #
b10000001 "
#130
b10 !
b10 (
b10 '
b10 &
b10000010 #
b10000010 "
#131
b11 !
b11 (
b11 '
b11 &
b10000011 #
b10000011 "
#132
b100 !
b100 (
b100 '
b100 &
b10000100 #
b10000100 "
#133
b101 !
b101 (
b101 '
b101 &
b10000101 #
b10000101 "
#134
b110 !
b110 (
b110 '
b110 &
b10000110 #
b10000110 "
#135
b111 !
b111 (
b111 '
b111 &
b10000111 #
b10000111 "
#136
b1000 !
b1000 (
b1000 '
b1000 &
b10001000 #
b10001000 "
#137
b1001 !
b1001 (
b1001 '
b1001 &
b10001001 #
b10001001 "
#138
b1010 !
b1010 (
b1010 '
b1010 &
b10001010 #
b10001010 "
#139
b1011 !
b1011 (
b1011 '
b1011 &
b10001011 #
b10001011 "
#140
b1100 !
b1100 (
b1100 '
b1100 &
b10001100 #
b10001100 "
#141
b1101 !
b1101 (
b1101 '
b1101 &
b10001101 #
b10001101 "
#142
b1110 !
b1110 (
b1110 '
b1110 &
b10001110 #
b10001110 "
#143
b1111 !
b1111 (
b1111 '
b1111 &
b10001111 #
b10001111 "
#144
b0 !
b0 (
b0 '
b0 &
b1001 %
b10010000 #
b10010000 "
#145
b1 !
b1 (
b1 '
b1 &
b10010001 #
b10010001 "
#146
b10 !
b10 (
b10 '
b10 &
b10010010 #
b10010010 "
#147
b11 !
b11 (
b11 '
b11 &
b10010011 #
b10010011 "
#148
b100 !
b100 (
b100 '
b100 &
b10010100 #
b10010100 "
#149
b101 !
b101 (
b101 '
b101 &
b10010101 #
b10010101 "
#150
b110 !
b110 (
b110 '
b110 &
b10010110 #
b10010110 "
#151
b111 !
b111 (
b111 '
b111 &
b10010111 #
b10010111 "
#152
b1000 !
b1000 (
b1000 '
b1000 &
b10011000 #
b10011000 "
#153
b1001 !
b1001 (
b1001 '
b1001 &
b10011001 #
b10011001 "
#154
b1010 !
b1010 (
b1010 '
b1010 &
b10011010 #
b10011010 "
#155
b1011 !
b1011 (
b1011 '
b1011 &
b10011011 #
b10011011 "
#156
b1100 !
b1100 (
b1100 '
b1100 &
b10011100 #
b10011100 "
#157
b1101 !
b1101 (
b1101 '
b1101 &
b10011101 #
b10011101 "
#158
b1110 !
b1110 (
b1110 '
b1110 &
b10011110 #
b10011110 "
#159
b1111 !
b1111 (
b1111 '
b1111 &
b10011111 #
b10011111 "
#160
b0 !
b0 (
b0 '
b0 &
b1010 %
b10100000 #
b10100000 "
#161
b1 !
b1 (
b1 '
b1 &
b10100001 #
b10100001 "
#162
b10 !
b10 (
b10 '
b10 &
b10100010 #
b10100010 "
#163
b11 !
b11 (
b11 '
b11 &
b10100011 #
b10100011 "
#164
b100 !
b100 (
b100 '
b100 &
b10100100 #
b10100100 "
#165
b101 !
b101 (
b101 '
b101 &
b10100101 #
b10100101 "
#166
b110 !
b110 (
b110 '
b110 &
b10100110 #
b10100110 "
#167
b111 !
b111 (
b111 '
b111 &
b10100111 #
b10100111 "
#168
b1000 !
b1000 (
b1000 '
b1000 &
b10101000 #
b10101000 "
#169
b1001 !
b1001 (
b1001 '
b1001 &
b10101001 #
b10101001 "
#170
b1010 !
b1010 (
b1010 '
b1010 &
b10101010 #
b10101010 "
#171
b1011 !
b1011 (
b1011 '
b1011 &
b10101011 #
b10101011 "
#172
b1100 !
b1100 (
b1100 '
b1100 &
b10101100 #
b10101100 "
#173
b1101 !
b1101 (
b1101 '
b1101 &
b10101101 #
b10101101 "
#174
b1110 !
b1110 (
b1110 '
b1110 &
b10101110 #
b10101110 "
#175
b1111 !
b1111 (
b1111 '
b1111 &
b10101111 #
b10101111 "
#176
b0 !
b0 (
b0 '
b0 &
b1011 %
b10110000 #
b10110000 "
#177
b1 !
b1 (
b1 '
b1 &
b10110001 #
b10110001 "
#178
b10 !
b10 (
b10 '
b10 &
b10110010 #
b10110010 "
#179
b11 !
b11 (
b11 '
b11 &
b10110011 #
b10110011 "
#180
b100 !
b100 (
b100 '
b100 &
b10110100 #
b10110100 "
#181
b101 !
b101 (
b101 '
b101 &
b10110101 #
b10110101 "
#182
b110 !
b110 (
b110 '
b110 &
b10110110 #
b10110110 "
#183
b111 !
b111 (
b111 '
b111 &
b10110111 #
b10110111 "
#184
b1000 !
b1000 (
b1000 '
b1000 &
b10111000 #
b10111000 "
#185
b1001 !
b1001 (
b1001 '
b1001 &
b10111001 #
b10111001 "
#186
b1010 !
b1010 (
b1010 '
b1010 &
b10111010 #
b10111010 "
#187
b1011 !
b1011 (
b1011 '
b1011 &
b10111011 #
b10111011 "
#188
b1100 !
b1100 (
b1100 '
b1100 &
b10111100 #
b10111100 "
#189
b1101 !
b1101 (
b1101 '
b1101 &
b10111101 #
b10111101 "
#190
b1110 !
b1110 (
b1110 '
b1110 &
b10111110 #
b10111110 "
#191
b1111 !
b1111 (
b1111 '
b1111 &
b10111111 #
b10111111 "
#192
b0 !
b0 (
b0 '
b0 &
b1100 %
b11000000 #
b11000000 "
#193
b1 !
b1 (
b1 '
b1 &
b11000001 #
b11000001 "
#194
b10 !
b10 (
b10 '
b10 &
b11000010 #
b11000010 "
#195
b11 !
b11 (
b11 '
b11 &
b11000011 #
b11000011 "
#196
b100 !
b100 (
b100 '
b100 &
b11000100 #
b11000100 "
#197
b101 !
b101 (
b101 '
b101 &
b11000101 #
b11000101 "
#198
b110 !
b110 (
b110 '
b110 &
b11000110 #
b11000110 "
#199
b111 !
b111 (
b111 '
b111 &
b11000111 #
b11000111 "
#200
b1000 !
b1000 (
b1000 '
b1000 &
b11001000 #
b11001000 "
#201
b1001 !
b1001 (
b1001 '
b1001 &
b11001001 #
b11001001 "
#202
b1010 !
b1010 (
b1010 '
b1010 &
b11001010 #
b11001010 "
#203
b1011 !
b1011 (
b1011 '
b1011 &
b11001011 #
b11001011 "
#204
b1100 !
b1100 (
b1100 '
b1100 &
b11001100 #
b11001100 "
#205
b1101 !
b1101 (
b1101 '
b1101 &
b11001101 #
b11001101 "
#206
b1110 !
b1110 (
b1110 '
b1110 &
b11001110 #
b11001110 "
#207
b1111 !
b1111 (
b1111 '
b1111 &
b11001111 #
b11001111 "
#208
b0 !
b0 (
b0 '
b0 &
b1101 %
b11010000 #
b11010000 "
#209
b1 !
b1 (
b1 '
b1 &
b11010001 #
b11010001 "
#210
b10 !
b10 (
b10 '
b10 &
b11010010 #
b11010010 "
#211
b11 !
b11 (
b11 '
b11 &
b11010011 #
b11010011 "
#212
b100 !
b100 (
b100 '
b100 &
b11010100 #
b11010100 "
#213
b101 !
b101 (
b101 '
b101 &
b11010101 #
b11010101 "
#214
b110 !
b110 (
b110 '
b110 &
b11010110 #
b11010110 "
#215
b111 !
b111 (
b111 '
b111 &
b11010111 #
b11010111 "
#216
b1000 !
b1000 (
b1000 '
b1000 &
b11011000 #
b11011000 "
#217
b1001 !
b1001 (
b1001 '
b1001 &
b11011001 #
b11011001 "
#218
b1010 !
b1010 (
b1010 '
b1010 &
b11011010 #
b11011010 "
#219
b1011 !
b1011 (
b1011 '
b1011 &
b11011011 #
b11011011 "
#220
b1100 !
b1100 (
b1100 '
b1100 &
b11011100 #
b11011100 "
#221
b1101 !
b1101 (
b1101 '
b1101 &
b11011101 #
b11011101 "
#222
b1110 !
b1110 (
b1110 '
b1110 &
b11011110 #
b11011110 "
#223
b1111 !
b1111 (
b1111 '
b1111 &
b11011111 #
b11011111 "
#224
b0 !
b0 (
b0 '
b0 &
b1110 %
b11100000 #
b11100000 "
#225
b1 !
b1 (
b1 '
b1 &
b11100001 #
b11100001 "
#226
b10 !
b10 (
b10 '
b10 &
b11100010 #
b11100010 "
#227
b11 !
b11 (
b11 '
b11 &
b11100011 #
b11100011 "
#228
b100 !
b100 (
b100 '
b100 &
b11100100 #
b11100100 "
#229
b101 !
b101 (
b101 '
b101 &
b11100101 #
b11100101 "
#230
b110 !
b110 (
b110 '
b110 &
b11100110 #
b11100110 "
#231
b111 !
b111 (
b111 '
b111 &
b11100111 #
b11100111 "
#232
b1000 !
b1000 (
b1000 '
b1000 &
b11101000 #
b11101000 "
#233
b1001 !
b1001 (
b1001 '
b1001 &
b11101001 #
b11101001 "
#234
b1010 !
b1010 (
b1010 '
b1010 &
b11101010 #
b11101010 "
#235
b1011 !
b1011 (
b1011 '
b1011 &
b11101011 #
b11101011 "
#236
b1100 !
b1100 (
b1100 '
b1100 &
b11101100 #
b11101100 "
#237
b1101 !
b1101 (
b1101 '
b1101 &
b11101101 #
b11101101 "
#238
b1110 !
b1110 (
b1110 '
b1110 &
b11101110 #
b11101110 "
#239
b1111 !
b1111 (
b1111 '
b1111 &
b11101111 #
b11101111 "
#240
b0 !
b0 (
b0 '
b0 &
b1111 %
b11110000 #
b11110000 "
#241
b1 !
b1 (
b1 '
b1 &
b11110001 #
b11110001 "
#242
b10 !
b10 (
b10 '
b10 &
b11110010 #
b11110010 "
#243
b11 !
b11 (
b11 '
b11 &
b11110011 #
b11110011 "
#244
b100 !
b100 (
b100 '
b100 &
b11110100 #
b11110100 "
#245
b101 !
b101 (
b101 '
b101 &
b11110101 #
b11110101 "
#246
b110 !
b110 (
b110 '
b110 &
b11110110 #
b11110110 "
#247
b111 !
b111 (
b111 '
b111 &
b11110111 #
b11110111 "
#248
b1000 !
b1000 (
b1000 '
b1000 &
b11111000 #
b11111000 "
#249
b1001 !
b1001 (
b1001 '
b1001 &
b11111001 #
b11111001 "
#250
b1010 !
b1010 (
b1010 '
b1010 &
b11111010 #
b11111010 "
#251
b1011 !
b1011 (
b1011 '
b1011 &
b11111011 #
b11111011 "
#252
b1100 !
b1100 (
b1100 '
b1100 &
b11111100 #
b11111100 "
#253
b1101 !
b1101 (
b1101 '
b1101 &
b11111101 #
b11111101 "
#254
b1110 !
b1110 (
b1110 '
b1110 &
b11111110 #
b11111110 "
#255
b1111 !
b1111 (
b1111 '
b1111 &
b11111111 #
b11111111 "
#256
b0 !
b0 (
b0 '
b0 &
b0 %
b100000000 #
b100000000 "
#257
b1 !
b1 (
b1 '
b1 &
b100000001 #
b100000001 "
#258
b10 !
b10 (
b10 '
b10 &
b100000010 #
b100000010 "
#259
b11 !
b11 (
b11 '
b11 &
b100000011 #
b100000011 "
#260
b100 !
b100 (
b100 '
b100 &
b100000100 #
b100000100 "
#261
b101 !
b101 (
b101 '
b101 &
b100000101 #
b100000101 "
#262
b110 !
b110 (
b110 '
b110 &
b100000110 #
b100000110 "
#263
b111 !
b111 (
b111 '
b111 &
b100000111 #
b100000111 "
#264
b1000 !
b1000 (
b1000 '
b1000 &
b100001000 #
b100001000 "
#265
b1001 !
b1001 (
b1001 '
b1001 &
b100001001 #
b100001001 "
#266
b1010 !
b1010 (
b1010 '
b1010 &
b100001010 #
b100001010 "
#267
b1011 !
b1011 (
b1011 '
b1011 &
b100001011 #
b100001011 "
#268
b1100 !
b1100 (
b1100 '
b1100 &
b100001100 #
b100001100 "
#269
b1101 !
b1101 (
b1101 '
b1101 &
b100001101 #
b100001101 "
#270
b1110 !
b1110 (
b1110 '
b1110 &
b100001110 #
b100001110 "
#271
b1111 !
b1111 (
b1111 '
b1111 &
b100001111 #
b100001111 "
#272
b0 !
b0 (
b0 '
b0 &
b1 %
b100010000 #
b100010000 "
#273
b1 !
b1 (
b1 '
b1 &
b100010001 #
b100010001 "
#274
b10 !
b10 (
b10 '
b10 &
b100010010 #
b100010010 "
#275
b11 !
b11 (
b11 '
b11 &
b100010011 #
b100010011 "
#276
b100 !
b100 (
b100 '
b100 &
b100010100 #
b100010100 "
#277
b101 !
b101 (
b101 '
b101 &
b100010101 #
b100010101 "
#278
b110 !
b110 (
b110 '
b110 &
b100010110 #
b100010110 "
#279
b111 !
b111 (
b111 '
b111 &
b100010111 #
b100010111 "
#280
b1000 !
b1000 (
b1000 '
b1000 &
b100011000 #
b100011000 "
#281
b1001 !
b1001 (
b1001 '
b1001 &
b100011001 #
b100011001 "
#282
b1010 !
b1010 (
b1010 '
b1010 &
b100011010 #
b100011010 "
#283
b1011 !
b1011 (
b1011 '
b1011 &
b100011011 #
b100011011 "
#284
b1100 !
b1100 (
b1100 '
b1100 &
b100011100 #
b100011100 "
#285
b1101 !
b1101 (
b1101 '
b1101 &
b100011101 #
b100011101 "
#286
b1110 !
b1110 (
b1110 '
b1110 &
b100011110 #
b100011110 "
#287
b1111 !
b1111 (
b1111 '
b1111 &
b100011111 #
b100011111 "
#288
b0 !
b0 (
b0 '
b0 &
b10 %
b100100000 #
b100100000 "
#289
b1 !
b1 (
b1 '
b1 &
b100100001 #
b100100001 "
#290
b10 !
b10 (
b10 '
b10 &
b100100010 #
b100100010 "
#291
b11 !
b11 (
b11 '
b11 &
b100100011 #
b100100011 "
#292
b100 !
b100 (
b100 '
b100 &
b100100100 #
b100100100 "
#293
b101 !
b101 (
b101 '
b101 &
b100100101 #
b100100101 "
#294
b110 !
b110 (
b110 '
b110 &
b100100110 #
b100100110 "
#295
b111 !
b111 (
b111 '
b111 &
b100100111 #
b100100111 "
#296
b1000 !
b1000 (
b1000 '
b1000 &
b100101000 #
b100101000 "
#297
b1001 !
b1001 (
b1001 '
b1001 &
b100101001 #
b100101001 "
#298
b1010 !
b1010 (
b1010 '
b1010 &
b100101010 #
b100101010 "
#299
b1011 !
b1011 (
b1011 '
b1011 &
b100101011 #
b100101011 "
#300
b1100 !
b1100 (
b1100 '
b1100 &
b100101100 #
b100101100 "
#301
b1101 !
b1101 (
b1101 '
b1101 &
b100101101 #
b100101101 "
#302
b1110 !
b1110 (
b1110 '
b1110 &
b100101110 #
b100101110 "
#303
b1111 !
b1111 (
b1111 '
b1111 &
b100101111 #
b100101111 "
#304
b0 !
b0 (
b0 '
b0 &
b11 %
b100110000 #
b100110000 "
#305
b1 !
b1 (
b1 '
b1 &
b100110001 #
b100110001 "
#306
b10 !
b10 (
b10 '
b10 &
b100110010 #
b100110010 "
#307
b11 !
b11 (
b11 '
b11 &
b100110011 #
b100110011 "
#308
b100 !
b100 (
b100 '
b100 &
b100110100 #
b100110100 "
#309
b101 !
b101 (
b101 '
b101 &
b100110101 #
b100110101 "
#310
b110 !
b110 (
b110 '
b110 &
b100110110 #
b100110110 "
#311
b111 !
b111 (
b111 '
b111 &
b100110111 #
b100110111 "
#312
b1000 !
b1000 (
b1000 '
b1000 &
b100111000 #
b100111000 "
#313
b1001 !
b1001 (
b1001 '
b1001 &
b100111001 #
b100111001 "
#314
b1010 !
b1010 (
b1010 '
b1010 &
b100111010 #
b100111010 "
#315
b1011 !
b1011 (
b1011 '
b1011 &
b100111011 #
b100111011 "
#316
b1100 !
b1100 (
b1100 '
b1100 &
b100111100 #
b100111100 "
#317
b1101 !
b1101 (
b1101 '
b1101 &
b100111101 #
b100111101 "
#318
b1110 !
b1110 (
b1110 '
b1110 &
b100111110 #
b100111110 "
#319
b1111 !
b1111 (
b1111 '
b1111 &
b100111111 #
b100111111 "
#320
b0 !
b0 (
b0 '
b0 &
b100 %
b101000000 #
b101000000 "
#321
b1 !
b1 (
b1 '
b1 &
b101000001 #
b101000001 "
#322
b10 !
b10 (
b10 '
b10 &
b101000010 #
b101000010 "
#323
b11 !
b11 (
b11 '
b11 &
b101000011 #
b101000011 "
#324
b100 !
b100 (
b100 '
b100 &
b101000100 #
b101000100 "
#325
b101 !
b101 (
b101 '
b101 &
b101000101 #
b101000101 "
#326
b110 !
b110 (
b110 '
b110 &
b101000110 #
b101000110 "
#327
b111 !
b111 (
b111 '
b111 &
b101000111 #
b101000111 "
#328
b1000 !
b1000 (
b1000 '
b1000 &
b101001000 #
b101001000 "
#329
b1001 !
b1001 (
b1001 '
b1001 &
b101001001 #
b101001001 "
#330
b1010 !
b1010 (
b1010 '
b1010 &
b101001010 #
b101001010 "
#331
b1011 !
b1011 (
b1011 '
b1011 &
b101001011 #
b101001011 "
#332
b1100 !
b1100 (
b1100 '
b1100 &
b101001100 #
b101001100 "
#333
b1101 !
b1101 (
b1101 '
b1101 &
b101001101 #
b101001101 "
#334
b1110 !
b1110 (
b1110 '
b1110 &
b101001110 #
b101001110 "
#335
b1111 !
b1111 (
b1111 '
b1111 &
b101001111 #
b101001111 "
#336
b0 !
b0 (
b0 '
b0 &
b101 %
b101010000 #
b101010000 "
#337
b1 !
b1 (
b1 '
b1 &
b101010001 #
b101010001 "
#338
b10 !
b10 (
b10 '
b10 &
b101010010 #
b101010010 "
#339
b11 !
b11 (
b11 '
b11 &
b101010011 #
b101010011 "
#340
b100 !
b100 (
b100 '
b100 &
b101010100 #
b101010100 "
#341
b101 !
b101 (
b101 '
b101 &
b101010101 #
b101010101 "
#342
b110 !
b110 (
b110 '
b110 &
b101010110 #
b101010110 "
#343
b111 !
b111 (
b111 '
b111 &
b101010111 #
b101010111 "
#344
b1000 !
b1000 (
b1000 '
b1000 &
b101011000 #
b101011000 "
#345
b1001 !
b1001 (
b1001 '
b1001 &
b101011001 #
b101011001 "
#346
b1010 !
b1010 (
b1010 '
b1010 &
b101011010 #
b101011010 "
#347
b1011 !
b1011 (
b1011 '
b1011 &
b101011011 #
b101011011 "
#348
b1100 !
b1100 (
b1100 '
b1100 &
b101011100 #
b101011100 "
#349
b1101 !
b1101 (
b1101 '
b1101 &
b101011101 #
b101011101 "
#350
b1110 !
b1110 (
b1110 '
b1110 &
b101011110 #
b101011110 "
#351
b1111 !
b1111 (
b1111 '
b1111 &
b101011111 #
b101011111 "
#352
b0 !
b0 (
b0 '
b0 &
b110 %
b101100000 #
b101100000 "
#353
b1 !
b1 (
b1 '
b1 &
b101100001 #
b101100001 "
#354
b10 !
b10 (
b10 '
b10 &
b101100010 #
b101100010 "
#355
b11 !
b11 (
b11 '
b11 &
b101100011 #
b101100011 "
#356
b100 !
b100 (
b100 '
b100 &
b101100100 #
b101100100 "
#357
b101 !
b101 (
b101 '
b101 &
b101100101 #
b101100101 "
#358
b110 !
b110 (
b110 '
b110 &
b101100110 #
b101100110 "
#359
b111 !
b111 (
b111 '
b111 &
b101100111 #
b101100111 "
#360
b1000 !
b1000 (
b1000 '
b1000 &
b101101000 #
b101101000 "
#361
b1001 !
b1001 (
b1001 '
b1001 &
b101101001 #
b101101001 "
#362
b1010 !
b1010 (
b1010 '
b1010 &
b101101010 #
b101101010 "
#363
b1011 !
b1011 (
b1011 '
b1011 &
b101101011 #
b101101011 "
#364
b1100 !
b1100 (
b1100 '
b1100 &
b101101100 #
b101101100 "
